gs_to_csv/__init__.py
gs_to_csv/cli.py
gs_to_csv/exporter.py
gs_to_csv/google_app_oauth_id.json
google_sheets_to_csv-0.2.0.dist-info/LICENSE
google_sheets_to_csv-0.2.0.dist-info/METADATA
google_sheets_to_csv-0.2.0.dist-info/WHEEL
google_sheets_to_csv-0.2.0.dist-info/entry_points.txt
google_sheets_to_csv-0.2.0.dist-info/top_level.txt
google_sheets_to_csv-0.2.0.dist-info/RECORD
