Metadata-Version: 2.1
Name: google-sheets-to-csv
Version: 0.2.0
Summary: Convert Google SpreadSheet document to CSV files
Home-page: https://gitlab.com/micro-entreprise/google-sheets-to-csv
Author: Pierre Verkest
Author-email: pierreverkest84@gmail.com
License: UNKNOWN
Platform: UNKNOWN
Classifier: Development Status :: 4 - Beta
Classifier: License :: OSI Approved :: Apache Software License
Classifier: Programming Language :: Python :: 3
Requires-Dist: google-api-python-client
Requires-Dist: google-auth-httplib2
Requires-Dist: google-auth-oauthlib
